usum/__init__.py
usum/__version__.py
usum/main.py
usum-0.1.6.dist-info/LICENSE.txt
usum-0.1.6.dist-info/METADATA
usum-0.1.6.dist-info/WHEEL
usum-0.1.6.dist-info/entry_points.txt
usum-0.1.6.dist-info/top_level.txt
usum-0.1.6.dist-info/RECORD
