Metadata-Version: 2.1
Name: usum
Version: 0.1.6
Summary: USUM: Plotting sequence similarity using USEARCH & UMAP
Home-page: https://github.com/prihoda/usum
Author: David Příhoda
Author-email: david.prihoda@gmail.com
License: MIT
Keywords: dna,protein,sequence,similarity,umap,usearch,uclust,plot
Platform: UNKNOWN
Requires-Python: >=3.6
Requires-Dist: biopython
Requires-Dist: umap-learn[plot]
